{
  "project_info": {
    "project_number": "623891134664",
    "project_id": "final-project-group-1",
    "storage_bucket": "final-project-group-1.firebasestorage.app"
  },
  "client": [
    {
      "client_info": {
        "mobilesdk_app_id": "1:623891134664:android:17d0911f7f5cbfcce8cdfd",
        "android_client_info": {
          "package_name": "com.example.final_project"
        }
      },
      "oauth_client": [],
      "api_key": [
        {
          "current_key": "AIzaSyBlfOXrwHuDVUfZkR5ys70X7pR4D_xEkwE"
        }
      ],
      "services": {
        "appinvite_service": {
          "other_platform_oauth_client": []
        }
      }
    }
  ],
  "configuration_version": "1"
}